sankeyfy/__init__.py
sankeyfy-0.2.dist-info/LICENSE.txt
sankeyfy-0.2.dist-info/METADATA
sankeyfy-0.2.dist-info/WHEEL
sankeyfy-0.2.dist-info/top_level.txt
sankeyfy-0.2.dist-info/RECORD
