Metadata-Version: 2.1
Name: sankeyfy
Version: 0.2
Summary: Wrangle dataframes for use in Sankey visualizations
Home-page: https://github.com/MCBoarder289/sankeyfy
Author: Michael Chapman
Author-email: chapman.michael.c@gmail.com
License: MIT
Keywords: sankey plotly D3
Platform: UNKNOWN
Requires-Dist: numpy
Requires-Dist: pandas
